soilgrids/__init__.py
soilgrids/_version.py
soilgrids/bmi.py
soilgrids/cli.py
soilgrids/soilgrids.py
soilgrids-0.1.4.dist-info/LICENSE.txt
soilgrids-0.1.4.dist-info/METADATA
soilgrids-0.1.4.dist-info/WHEEL
soilgrids-0.1.4.dist-info/entry_points.txt
soilgrids-0.1.4.dist-info/top_level.txt
soilgrids-0.1.4.dist-info/RECORD
