Metadata-Version: 2.1
Name: soilgrids
Version: 0.1.4
Summary: Fetch global gridded soil information from the SoilGrids system https://www.isric.org/explore/soilgrids
Home-page: http://csdms.colorado.edu
Author: Tian Gan
Author-email: jamy127@foxmail.com
License-File: LICENSE.txt
Requires-Dist: bmipy
Requires-Dist: click
Requires-Dist: netcdf4
Requires-Dist: numpy
Requires-Dist: pyyaml
Requires-Dist: requests
Requires-Dist: rioxarray
Requires-Dist: xarray
Requires-Dist: owslib
